MANIFEST.in
README.md
setup.cfg
setup.py
topsis_Nandini_101903480/__init__.py
topsis_Nandini_101903480/topsis_Nandini_101903480.py
topsis_Nandini_101903480.egg-info/PKG-INFO
topsis_Nandini_101903480.egg-info/SOURCES.txt
topsis_Nandini_101903480.egg-info/dependency_links.txt
topsis_Nandini_101903480.egg-info/requires.txt
topsis_Nandini_101903480.egg-info/top_level.txt