Metadata-Version: 2.1
Name: topsis-Nandini-101903480
Version: 1.1
Summary: A Python package to rank ML models/choices using topsis technique
Home-page: https://github.com/nandiniseth0809/topsis-nandini-101903480
Author: Nandini Seth
Author-email: nandiniseth0809@gmail.com
License: MIT
Platform: UNKNOWN
Classifier: License :: OSI Approved :: MIT License
Classifier: Programming Language :: Python :: 3
Classifier: Programming Language :: Python :: 3.7
